{
  "timestamp": "2025-11-07T01:59:15.224775",
  "python": "3.11.0 (main, Oct 24 2022, 18:26:48) [MSC v.1933 64 bit (AMD64)]",
  "platform": "Windows-10-10.0.26200-SP0",
  "versions": {
    "numpy": "2.2.6",
    "pandas": "2.3.3",
    "sklearn": "1.7.2",
    "matplotlib": "3.10.7",
    "seaborn": "0.13.2"
  },
  "args": {
    "mode": "train_until_target",
    "target_acc": 0.85,
    "max_tries": 50,
    "data_path": "./dataset",
    "test_size": 0.2,
    "kernel": "rbf",
    "use_grid_search": true,
    "scoring": "f1",
    "cv_splits": 5,
    "cv_repeats": 3,
    "sliding": true,
    "win": 8000,
    "step": 4000,
    "group_split": true,
    "feature_selector": "mi"
  },
  "seed": 17,
  "data": {
    "fatigue_files_sorted": [
      "Christi_F.csv",
      "Faris_F.csv",
      "Hasna_F.csv",
      "Khayla_F.csv",
      "Nazla_F.csv",
      "Niken_F.csv",
      "Rona_F.csv",
      "Shalsa_F.csv",
      "aida_F.csv",
      "aldhito_F.csv",
      "azka_F.csv",
      "caca_F.csv",
      "giselle_F - Copy.csv",
      "insan_F.csv",
      "ipul_F.csv",
      "iqbal_F.h5.csv",
      "jeki_F.csv",
      "nae_F.csv",
      "nazhir_F.csv",
      "niko_F.csv",
      "putri_F.csv",
      "raffa_F.csv",
      "sipa_F.csv",
      "tarisa_F.csv",
      "tyo_F.csv",
      "umar_F.csv"
    ],
    "non_fatigue_files_sorted": [
      "Christi_NF.csv",
      "Faris_NF.csv",
      "Hasna_NF.csv",
      "Khayla_NF.csv",
      "Nae_NF.csv",
      "Nazla_NF.csv",
      "Rona_NF.csv",
      "Shalsa_NF.csv",
      "aida_NF.csv",
      "aldhito_NF.csv",
      "azka_NF.csv",
      "caca_NF.csv",
      "giselle_NF.csv",
      "insan_NF.csv",
      "ipul_NF.csv",
      "iqbal_NF.csv",
      "jeki_NF.csv",
      "nazhir_NF.csv",
      "niken_NF.csv",
      "niko_NF.csv",
      "putri_NF.csv",
      "raffa_NF.csv",
      "syifa_NF.csv",
      "tarisa_NF.csv",
      "tyo_NF.csv",
      "umar_NF.csv"
    ],
    "train_idx": [
      0,
      1,
      2,
      3,
      4,
      5,
      6,
      7,
      8,
      9,
      10,
      11,
      12,
      13,
      14,
      15,
      16,
      17,
      18,
      19,
      20,
      21,
      22,
      23,
      24,
      25,
      26,
      27,
      28,
      29,
      30,
      31,
      32,
      33,
      34,
      35,
      36,
      37,
      38,
      39,
      40,
      41,
      42,
      43,
      44,
      45,
      46,
      47,
      48,
      49,
      50,
      51,
      52,
      53,
      54,
      55,
      56,
      57,
      58,
      59,
      60,
      61,
      62,
      63,
      64,
      65,
      66,
      67,
      68,
      69,
      70,
      71,
      72,
      73,
      74,
      75,
      76,
      77,
      78,
      79,
      80,
      81,
      82,
      83,
      84,
      85,
      86,
      87,
      88,
      89,
      90,
      91,
      92,
      93,
      94,
      95,
      96,
      97,
      98,
      99,
      100,
      101,
      102,
      103,
      104,
      105,
      106,
      107,
      108,
      109,
      110,
      111,
      112,
      113,
      114,
      115,
      116,
      117,
      118,
      119,
      120,
      121,
      122,
      123,
      124,
      125,
      126,
      127,
      128,
      129,
      130,
      131,
      132,
      133,
      134,
      135,
      136,
      137,
      138,
      139,
      140,
      141,
      142,
      143,
      144,
      145,
      146,
      147,
      148,
      149,
      150,
      151,
      152,
      153,
      154,
      155,
      156,
      157,
      158,
      159,
      160,
      161,
      162,
      163,
      164,
      165,
      166,
      167,
      168,
      169,
      170,
      182,
      183,
      184,
      185,
      186,
      187,
      188,
      189,
      190,
      191,
      192,
      213,
      214,
      215,
      216,
      217,
      218,
      219,
      220,
      221,
      222,
      223,
      235,
      236,
      237,
      238,
      239,
      240,
      241,
      242,
      243,
      244,
      245,
      270,
      271,
      272,
      273,
      274,
      275,
      276,
      277,
      278,
      279,
      280,
      281,
      282,
      283,
      284,
      285,
      286,
      287,
      288,
      289,
      290,
      291,
      292,
      293,
      294,
      295,
      296,
      297,
      298,
      299,
      300,
      301,
      302,
      303,
      304,
      305,
      306,
      307,
      308,
      309,
      310,
      311,
      312,
      313,
      314,
      315,
      316,
      317,
      318,
      319,
      320,
      321,
      322,
      323,
      324,
      336,
      337,
      338,
      339,
      340,
      341,
      342,
      343,
      344,
      345,
      346,
      347,
      348,
      349,
      350,
      351,
      352,
      353,
      354,
      355,
      356,
      357,
      358,
      359,
      360,
      361,
      362,
      363,
      364,
      365,
      366,
      367,
      368,
      369,
      370,
      371,
      372,
      373,
      374,
      375,
      376,
      377,
      378,
      379,
      380,
      381,
      382,
      383,
      384,
      385,
      386,
      387,
      388,
      389,
      390,
      391,
      392,
      393,
      394,
      395,
      396,
      397,
      398,
      399,
      400,
      401,
      402,
      403,
      404,
      405,
      406,
      407,
      408,
      409,
      410,
      411,
      412,
      413,
      414,
      415,
      416,
      417,
      418,
      419,
      420,
      421,
      422,
      423,
      424,
      425,
      426,
      427,
      428,
      429,
      430,
      431,
      432,
      433,
      434,
      435,
      436,
      437,
      438,
      439,
      440,
      441,
      442,
      443,
      444,
      445,
      446,
      447,
      448,
      449,
      450,
      484,
      485,
      486,
      487,
      488,
      489,
      490,
      491,
      492,
      493,
      494,
      495,
      496,
      497,
      498,
      499,
      500,
      501,
      502,
      503,
      504,
      505,
      506,
      507,
      508,
      509,
      510,
      511,
      512,
      513,
      514,
      515,
      516,
      517,
      518,
      519,
      520,
      521,
      522,
      523,
      524,
      525,
      526,
      527,
      528,
      529,
      530,
      531,
      532,
      533,
      544,
      545,
      546,
      547,
      548,
      549,
      550,
      551,
      552,
      553,
      554
    ],
    "test_idx": [
      171,
      172,
      173,
      174,
      175,
      176,
      177,
      178,
      179,
      180,
      181,
      193,
      194,
      195,
      196,
      197,
      198,
      199,
      200,
      201,
      202,
      203,
      204,
      205,
      206,
      207,
      208,
      209,
      210,
      211,
      212,
      224,
      225,
      226,
      227,
      228,
      229,
      230,
      231,
      232,
      233,
      234,
      246,
      247,
      248,
      249,
      250,
      251,
      252,
      253,
      254,
      255,
      256,
      257,
      258,
      259,
      260,
      261,
      262,
      263,
      264,
      265,
      266,
      267,
      268,
      269,
      325,
      326,
      327,
      328,
      329,
      330,
      331,
      332,
      333,
      334,
      335,
      451,
      452,
      453,
      454,
      455,
      456,
      457,
      458,
      459,
      460,
      461,
      462,
      463,
      464,
      465,
      466,
      467,
      468,
      469,
      470,
      471,
      472,
      473,
      474,
      475,
      476,
      477,
      478,
      479,
      480,
      481,
      482,
      483,
      534,
      535,
      536,
      537,
      538,
      539,
      540,
      541,
      542,
      543
    ]
  },
  "preprocess": {
    "fs": 1000.0,
    "lowcut": 10.0,
    "highcut": 100.0,
    "notch_hz": 50.0,
    "ranges_to_keep": [
      [
        15000,
        25000
      ],
      [
        30000,
        35000
      ]
    ],
    "sliding": true,
    "win": 8000,
    "step": 4000,
    "group_split": true,
    "feature_selector": "mi"
  },
  "features": {
    "k_selected": 20,
    "selected_feature_indices": [
      4,
      8,
      13,
      16,
      19,
      21,
      28,
      29,
      32,
      33,
      35,
      47,
      49,
      54,
      62,
      64,
      65,
      66,
      68,
      69
    ],
    "scaler_mean": [
      -0.006209619478297462,
      0.8663073434637608,
      0.8891725493330765,
      6.586997487259475,
      -0.8410982960872853,
      -0.25912980539717434,
      -0.5831701879342687,
      0.2935065301015481,
      0.95943048634308,
      0.6141481826870404,
      1193.7711698863775,
      506.1954022988506,
      605.8689655172413,
      2.6573751968082653,
      18.30267444038159,
      0.001445550406933296,
      0.0033645919187961864,
      0.036246501931547645,
      0.7219006557868619,
      0.166491111511993,
      0.10797497519234546,
      0.062426566444625166,
      68.7820575972274,
      48.38811063218391,
      68.7820575972274,
      0.00620961947829747,
      0.8811667582181375,
      0.8953019486232484,
      6.720135796098585,
      -0.8410939190682366,
      -0.2440263307582092,
      -0.5761345350377189,
      0.30891332299347646,
      0.9618274081276197,
      0.6197360902751358,
      1214.8136558698284,
      505.1816091954023,
      604.919540229885,
      2.6368548464019916,
      18.53896405433009,
      0.0013425359954193673,
      0.0030091305720316756,
      0.03146331047124406,
      0.6708417328543053,
      0.15263831989125806,
      0.10171887070047719,
      0.059449880244575794,
      68.88191744048409,
      48.50933908045977,
      68.88191744048409,
      1.4976525766667602e-18,
      0.9999999999995007,
      0.9999999999989967,
      9.18021160538769,
      -0.8412556230096938,
      -0.33800288375795334,
      -0.641877469536924,
      0.3158929843173521,
      0.9999999999995007,
      0.6927330379353915,
      2408.8797494660175,
      1011.5011494252874,
      1211.0781609195403,
      3.0470464376759394,
      26.362424902490574,
      0.0013879173465231502,
      0.0030148369883788158,
      0.030824234264406905,
      0.6932351533201133,
      0.15885977659479308,
      0.10419119836039,
      0.06056434882196322,
      69.25031085124066,
      47.876257183908045,
      69.25031085124066
    ],
    "scaler_scale": [
      0.3282136372041375,
      0.37240319009621786,
      0.522213079695624,
      4.518329649857732,
      0.280816757484218,
      0.2653408261511283,
      0.1828501499532607,
      0.5134094149692834,
      0.27645694462138865,
      0.27532695781095645,
      640.5705452017902,
      51.5634725653643,
      45.21426717753047,
      2.004073504640342,
      26.624685995687447,
      0.0009458631594544491,
      0.0025040386392932977,
      0.037275305418645446,
      0.47297910300299567,
      0.12477880390023519,
      0.07573385889958616,
      0.048436882130007054,
      15.50802107534979,
      23.340376213364735,
      15.50802107534979,
      0.3282136372041375,
      0.3447420671089996,
      0.4880957693468283,
      4.558111920790851,
      0.2808336316383988,
      0.3109750484375866,
      0.21169417541619837,
      0.5189699128024066,
      0.27920017302750466,
      0.25709201112627456,
      646.4244513086813,
      51.373069846530186,
      44.01489256609294,
      2.0949648109314998,
      29.80011343899607,
      0.0009018270558923036,
      0.0022570721163918993,
      0.034568493526395475,
      0.45091268270185997,
      0.11392446861808152,
      0.07237111552601959,
      0.04618917378836777,
      15.568375776625581,
      23.026987292694066,
      15.568375776625581,
      7.858910019779945e-17,
      8.058743732498946e-13,
      1.6117474903193937e-12,
      4.740914526802246,
      0.2808803357431486,
      0.12517048721957297,
      0.1525785394800612,
      0.21250093748303897,
      8.058696140509552e-13,
      0.12478154626861893,
      889.9721250077189,
      96.06308690306327,
      82.59399859259952,
      2.7098674769306044,
      52.74438604281956,
      0.0005003672888485959,
      0.0013332208822469474,
      0.025439802383419783,
      0.25076471031536024,
      0.06763936049670734,
      0.05039604369971351,
      0.031544070698242645,
      12.882059199995993,
      20.301397408968246,
      12.882059199995993
    ]
  },
  "model": {
    "svm_params": {
      "steps": [
        "scaler",
        "kbest",
        "svc"
      ],
      "kbest_k": 20,
      "svc": {
        "kernel": "rbf",
        "C": 0.01,
        "gamma": "scale",
        "degree": 3,
        "class_weight": "balanced",
        "probability": true,
        "random_state": 17
      }
    },
    "best_params": {
      "kbest__k": 20,
      "svc__C": 0.01,
      "svc__gamma": "scale",
      "svc__kernel": "rbf"
    }
  },
  "metrics": {
    "train_acc": 0.4942528735632184,
    "test_acc": 0.55,
    "auc": 0.5597643097643097
  },
  "files": {
    "confusion_matrix": "C:\\Users\\Mai Hieu\\Desktop\\DOAN\\phanloaimoico\\run_artifacts_target_seed_17\\SVM_target_seed17_Confusion_Matrix.png",
    "roc_curve": "C:\\Users\\Mai Hieu\\Desktop\\DOAN\\phanloaimoico\\run_artifacts_target_seed_17\\SVM_target_seed17_ROC_Curve.png"
  }
}